sportypy/__init__.py
sportypy/_base_classes/__init__.py
sportypy/_base_classes/_base_feature.py
sportypy/_base_classes/_base_surface.py
sportypy/_base_classes/_base_surface_plot.py
sportypy/_base_functions/__init__.py
sportypy/_base_functions/_base_shapes.py
sportypy/_base_functions/_coordinate_transformations.py
sportypy/_base_functions/_plot_helpers.py
sportypy/_feature_classes/__init__.py
sportypy/_feature_classes/baseball.py
sportypy/_feature_classes/basketball.py
sportypy/_feature_classes/curling.py
sportypy/_feature_classes/football.py
sportypy/_feature_classes/hockey.py
sportypy/_feature_classes/soccer.py
sportypy/_feature_classes/tennis.py
sportypy/data/__init__.py
sportypy/data/surface_dimensions.json
sportypy/data/unit_conversions.json
sportypy/surfaces/__init__.py
sportypy/surfaces/baseball.py
sportypy/surfaces/basketball.py
sportypy/surfaces/curling.py
sportypy/surfaces/football.py
sportypy/surfaces/hockey.py
sportypy/surfaces/soccer.py
sportypy/surfaces/tennis.py
sportypy-1.0.0.dist-info/LICENSE
sportypy-1.0.0.dist-info/METADATA
sportypy-1.0.0.dist-info/WHEEL
sportypy-1.0.0.dist-info/top_level.txt
sportypy-1.0.0.dist-info/RECORD
