Metadata-Version: 2.1
Name: sportypy
Version: 1.0.0
Summary: Draw sports surfaces according to rulebook specifications
Home-page: https://github.com/sportsdataverse/sportypy
Author: Ross Drucker
Author-email: ross.a.drucker@gmail.com
Maintainer: Ross Drucker
License: GPL 3.0
Project-URL: Source, https://github.com/sportsdataverse/sportypy
Project-URL: Docs, https://sportypy.sportsdataverse.org/
Project-URL: Bug Tracker, https://github.com/sportsdataverse/sportypy/issues
Classifier: License :: OSI Approved :: GNU General Public License v3 (GPLv3)
Classifier: Programming Language :: Python :: 3
Classifier: Programming Language :: Python :: 3.6
Classifier: Programming Language :: Python :: 3.7
Classifier: Programming Language :: Python :: 3.8
Classifier: Programming Language :: Python :: 3.9
Classifier: Programming Language :: Python :: 3.10
License-File: LICENSE
Requires-Dist: numpy
Requires-Dist: scipy
Requires-Dist: pandas
Requires-Dist: matplotlib
Provides-Extra: docs
Requires-Dist: sphinx ; extra == 'docs'
Requires-Dist: livereload ; extra == 'docs'
Requires-Dist: myst-parser ; extra == 'docs'
Requires-Dist: sphinx-markdown-builder ; extra == 'docs'
Requires-Dist: sphinx-bootstrap-theme ; extra == 'docs'
Provides-Extra: test
Requires-Dist: flake8 ; extra == 'test'
Requires-Dist: pytest ; extra == 'test'
Requires-Dist: pydocstyle ; extra == 'test'
Requires-Dist: pycodestyle ; extra == 'test'
